bayes_cn_hfs/__init__.py
bayes_cn_hfs/_version.py
bayes_cn_hfs/cn_model.py
bayes_cn_hfs/cn_ratio_model.py
bayes_cn_hfs/physics.py
bayes_cn_hfs/utils.py
bayes_cn_hfs-2.0.1.dist-info/licenses/LICENSE
bayes_cn_hfs-2.0.1.dist-info/METADATA
bayes_cn_hfs-2.0.1.dist-info/WHEEL
bayes_cn_hfs-2.0.1.dist-info/top_level.txt
bayes_cn_hfs-2.0.1.dist-info/RECORD
