Metadata-Version: 2.4
Name: bayes_cn_hfs
Version: 2.0.1
Summary: A Bayesian CN Hyperfine Spectral Model
Home-page: https://github.com/tvwenger/bayes_cn_hfs
Author: Trey V. Wenger
Author-email: Trey Wenger <tvwenger@gmail.com>
License: The MIT License (MIT)
Project-URL: Homepage, https://github.com/tvwenger/bayes_cn_hfs
Classifier: Programming Language :: Python :: 3
Classifier: License :: OSI Approved :: MIT License
Classifier: Operating System :: OS Independent
Requires-Python: >=3.11
License-File: LICENSE
Requires-Dist: astropy
Requires-Dist: astroquery
Requires-Dist: bayes_spec>=1.7.8
Dynamic: author
Dynamic: home-page
Dynamic: license-file
Dynamic: requires-python
